{"atoms":[{"atomic_number":8,"coordinates":[0.1921,2.6659,-4.0e-4]},{"atomic_number":7,"coordinates":[-2.0715,0.6588,6.0e-4]},{"atomic_number":7,"coordinates":[1.574,0.8031,1.0e-4]},{"atomic_number":7,"coordinates":[0.7566,-1.4536,-3.0e-4]},{"atomic_number":7,"coordinates":[-1.7194,-1.5432,-6.0e-4]},{"atomic_number":7,"coordinates":[3.0549,-1.01,5.0e-4]},{"atomic_number":6,"coordinates":[-0.718,0.4885,-1.0e-4]},{"atomic_number":6,"coordinates":[-0.5245,-0.8731,-4.0e-4]},{"atomic_number":6,"coordinates":[0.3383,1.4486,-1.0e-4]},{"atomic_number":6,"coordinates":[1.7483,-0.5924,0]},{"atomic_number":6,"coordinates":[-2.6308,-0.5926,5.0e-4]},{"atomic_number":1,"coordinates":[-2.5706,1.5386,1.2e-3]},{"atomic_number":1,"coordinates":[2.4078,1.3835,3.0e-4]},{"atomic_number":1,"coordinates":[-3.7015,-0.7392,1.0e-3]},{"atomic_number":1,"coordinates":[3.2905,-1.9965,6.0e-4]},{"atomic_number":1,"coordinates":[3.8223,-0.3471,8.0e-4]}],"bonds":[[0,8,2],[1,6,1],[1,10,1],[1,11,1],[2,8,1],[2,9,1],[2,12,1],[3,7,1],[3,9,2],[4,7,1],[4,10,2],[5,9,1],[5,14,1],[5,15,1],[6,7,2],[6,8,1],[10,13,1]]}